gocomics/__init__.py
gocomics/comic.py
gocomics/endpoints.py
gocomics/utils.py
gocomics_py-2.1.0.dist-info/licenses/LICENSE
gocomics_py-2.1.0.dist-info/METADATA
gocomics_py-2.1.0.dist-info/WHEEL
gocomics_py-2.1.0.dist-info/top_level.txt
gocomics_py-2.1.0.dist-info/RECORD
