Metadata-Version: 2.4
Name: gocomics.py
Version: 2.1.0
Summary: Fetch comics from GoComics.
Home-page: https://github.com/Ombucha/gocomics.py
Author: Omkaar
Author-email: omkaar.nerurkar@gmail.com
License: MIT
Classifier: License :: OSI Approved :: MIT License
Classifier: Natural Language :: English
Classifier: Programming Language :: Python
Classifier: Programming Language :: Python :: 3
Requires-Python: >= 3.8.0
License-File: LICENSE
Requires-Dist: beautifulsoup4
Requires-Dist: requests
Dynamic: author
Dynamic: author-email
Dynamic: classifier
Dynamic: description
Dynamic: description-content-type
Dynamic: home-page
Dynamic: license
Dynamic: license-file
Dynamic: requires-dist
Dynamic: requires-python
Dynamic: summary
